[
  {
    "id": "practice-analyst-evaluation-challenge",
    "title": "Analyst evaluation challenge",
    "provider": "AI Training Pathfinder",
    "description": "Evaluate a fictional AI-generated summary against fictional source notes and identify unsupported claims.",
    "professionalFields": ["Intelligence, research, and analysis", "Other"],
    "workPatterns": ["analyze-information"],
    "practicalFluencyLevels": ["foundational-user", "applied-user", "advanced-practitioner"],
    "technicalOrientations": ["general-user", "productivity-low-code", "developer-data-practitioner"],
    "estimatedMinutes": 25,
    "format": "Hands-on exercise or lab",
    "formatId": "hands-on-lab",
    "learningGoals": ["research-analysis", "evaluate-outputs"],
    "responsibilityIds": ["own-tasks", "review-others", "supervise-approve"],
    "pathStage": "Hands-on practice",
    "fictionalScenario": "A fictional regional office asks for a summary of three public news-style notes about a fictional supply trend.",
    "steps": [
      "Review the fictional notes and the AI-generated summary.",
      "Mark each AI claim as supported, unsupported, or uncertain.",
      "Rewrite the summary with uncertainty labels and source references."
    ],
    "deliverable": "A short claim-check table and revised nonsensitive summary.",
    "safetyReminder": "Use only the fictional material provided by the card.",
    "active": true
  },
  {
    "id": "practice-planning-assumptions-challenge",
    "title": "Planning assumptions challenge",
    "provider": "AI Training Pathfinder",
    "description": "Use fictional planning data to compare options, surface assumptions, and decide what requires human judgment.",
    "professionalFields": ["Operations and mission planning", "Leadership, policy, and governance", "Other"],
    "workPatterns": ["plan-decide", "lead-govern"],
    "practicalFluencyLevels": ["foundational-user", "applied-user", "advanced-practitioner"],
    "technicalOrientations": ["general-user", "productivity-low-code"],
    "estimatedMinutes": 30,
    "format": "Hands-on exercise or lab",
    "formatId": "hands-on-lab",
    "learningGoals": ["evaluate-outputs", "responsible-use-risk", "supervise-ai-work"],
    "responsibilityIds": ["review-others", "supervise-approve", "policy-risk"],
    "pathStage": "Hands-on practice",
    "fictionalScenario": "A fictional event team needs to compare three venue support options using nonsensitive schedule, staffing, and weather assumptions.",
    "steps": [
      "Identify assumptions in the fictional AI-generated option comparison.",
      "Separate factual claims from judgment calls.",
      "List follow-up questions a human planner should resolve."
    ],
    "deliverable": "An assumption log and human-review checklist.",
    "safetyReminder": "Do not substitute real operational plans, locations, units, or schedules.",
    "active": true
  },
  {
    "id": "practice-maintenance-troubleshooting-workflow",
    "title": "Maintenance troubleshooting workflow challenge",
    "provider": "AI Training Pathfinder",
    "description": "Use fictional maintenance tickets to design an AI-assisted triage workflow with human review points.",
    "professionalFields": ["Maintenance", "Administration and general support", "Other"],
    "workPatterns": ["sustain-optimize", "plan-decide"],
    "practicalFluencyLevels": ["foundational-user", "applied-user", "advanced-practitioner"],
    "technicalOrientations": ["general-user", "productivity-low-code", "developer-data-practitioner"],
    "estimatedMinutes": 25,
    "format": "Hands-on exercise or lab",
    "formatId": "hands-on-lab",
    "learningGoals": ["automate-repetitive-tasks", "evaluate-outputs", "generative-ai-productivity"],
    "responsibilityIds": ["own-tasks", "review-others", "supervise-approve"],
    "pathStage": "Hands-on practice",
    "fictionalScenario": "A fictional facilities team has five nonsensitive service tickets about generic equipment checks.",
    "steps": [
      "Group fictional tickets by likely cause and urgency.",
      "Draft an AI-assisted triage prompt that uses only nonsensitive ticket text.",
      "Add review points before any action is assigned."
    ],
    "deliverable": "A triage prompt, workflow sketch, and review checklist.",
    "safetyReminder": "Do not use actual maintenance data, equipment identifiers, or readiness information.",
    "active": true
  },
  {
    "id": "practice-logistics-demand-workflow",
    "title": "Logistics demand-planning workflow challenge",
    "provider": "AI Training Pathfinder",
    "description": "Use fictional supply requests to design an AI-assisted demand review workflow with human approval points.",
    "professionalFields": ["Logistics", "Administration and general support", "Other"],
    "workPatterns": ["sustain-optimize", "plan-decide", "analyze-information"],
    "practicalFluencyLevels": ["foundational-user", "applied-user", "advanced-practitioner"],
    "technicalOrientations": ["general-user", "productivity-low-code", "developer-data-practitioner"],
    "estimatedMinutes": 25,
    "format": "Hands-on exercise or lab",
    "formatId": "hands-on-lab",
    "learningGoals": ["automate-repetitive-tasks", "evaluate-outputs", "work-with-data"],
    "responsibilityIds": ["own-tasks", "review-others", "supervise-approve"],
    "pathStage": "Hands-on practice",
    "fictionalScenario": "A fictional supply office has six nonsensitive requests for generic classroom and office materials.",
    "steps": [
      "Group fictional requests by urgency, uncertainty, and likely follow-up needed.",
      "Draft an AI-assisted review prompt that uses only nonsensitive request text.",
      "Add human approval points before ordering, substitution, or priority decisions."
    ],
    "deliverable": "A demand-review prompt, workflow sketch, and human-approval checklist.",
    "safetyReminder": "Do not use actual supply data, locations, unit names, readiness information, or operational requirements.",
    "active": true
  },
  {
    "id": "practice-leadership-human-approval",
    "title": "Leadership and human-approval challenge",
    "provider": "AI Training Pathfinder",
    "description": "Review a fictional AI-assisted recommendation and decide what must remain a human decision.",
    "professionalFields": ["Leadership, policy, and governance", "Acquisition and program management", "Other"],
    "workPatterns": ["lead-govern", "plan-decide"],
    "practicalFluencyLevels": ["foundational-user", "applied-user", "advanced-practitioner"],
    "technicalOrientations": ["general-user", "productivity-low-code", "developer-data-practitioner"],
    "estimatedMinutes": 20,
    "format": "Hands-on exercise or lab",
    "formatId": "hands-on-lab",
    "learningGoals": ["supervise-ai-work", "responsible-use-risk", "evaluate-outputs"],
    "responsibilityIds": ["review-others", "supervise-approve", "policy-risk"],
    "pathStage": "Hands-on practice",
    "fictionalScenario": "A fictional team receives an AI-generated recommendation about prioritizing three generic training requests.",
    "steps": [
      "Identify where the AI recommendation is useful and where it overreaches.",
      "Define approval criteria and accountability boundaries.",
      "Write a short review note explaining the final human decision."
    ],
    "deliverable": "A human-approval checklist and review note.",
    "safetyReminder": "Use only fictional training-request details.",
    "active": true
  },
  {
    "id": "practice-trainer-audience-adaptation",
    "title": "Trainer audience-adaptation challenge",
    "provider": "AI Training Pathfinder",
    "description": "Adapt fictional AI-training content for two different nonsensitive learner audiences.",
    "professionalFields": ["Education, training, and communication", "Leadership, policy, and governance", "Other"],
    "workPatterns": ["create-communicate", "lead-govern"],
    "practicalFluencyLevels": ["new-to-ai", "foundational-user", "applied-user"],
    "technicalOrientations": ["general-user", "productivity-low-code"],
    "estimatedMinutes": 25,
    "format": "Hands-on exercise or lab",
    "formatId": "hands-on-lab",
    "learningGoals": ["teach-others", "writing-communication", "responsible-use-risk"],
    "responsibilityIds": ["own-tasks", "review-others", "supervise-approve"],
    "pathStage": "Hands-on practice",
    "fictionalScenario": "A fictional training office needs a short AI safety lesson adapted for new users and experienced reviewers.",
    "steps": [
      "Compare two fictional audience profiles.",
      "Rewrite the lesson objective and examples for each audience.",
      "Add a safety reminder about nonsensitive examples."
    ],
    "deliverable": "Two audience-adapted lesson outlines.",
    "safetyReminder": "Keep all examples fictional and broadly understandable.",
    "active": true
  },
  {
    "id": "practice-healthcare-privacy-verification",
    "title": "Healthcare privacy and verification challenge",
    "provider": "AI Training Pathfinder",
    "description": "Review a fictional wellness FAQ draft for privacy, verification, and human-review concerns.",
    "professionalFields": ["Healthcare", "Education, training, and communication", "Other"],
    "workPatterns": ["create-communicate", "analyze-information", "lead-govern"],
    "practicalFluencyLevels": ["new-to-ai", "foundational-user", "applied-user", "advanced-practitioner"],
    "technicalOrientations": ["general-user", "productivity-low-code"],
    "estimatedMinutes": 30,
    "format": "Hands-on exercise or lab",
    "formatId": "hands-on-lab",
    "learningGoals": ["responsible-use-risk", "evaluate-outputs", "writing-communication"],
    "responsibilityIds": ["own-tasks", "review-others", "supervise-approve", "policy-risk"],
    "pathStage": "Hands-on practice",
    "fictionalScenario": "A fictional wellness office has a generic AI-drafted FAQ about hydration and sleep hygiene.",
    "steps": [
      "Flag any claims that need authoritative verification.",
      "Identify wording that could be mistaken for medical advice.",
      "Rewrite the FAQ with clear limits and human-review language."
    ],
    "deliverable": "A privacy and verification review note plus revised FAQ excerpt.",
    "safetyReminder": "Do not use real patient, clinical, or protected health information.",
    "active": true
  }
]
